contentstore/__init__.py
contentstore/admin.py
contentstore/apps.py
contentstore/models.py
contentstore/serializers.py
contentstore/signals.py
contentstore/tasks.py
contentstore/urls.py
contentstore/views.py
contentstore/management/__init__.py
contentstore/management/commands/__init__.py
contentstore/management/commands/sync_schedules.py
contentstore/management/commands/tests/__init__.py
contentstore/management/commands/tests/test_sync_schedules.py
contentstore/migrations/0001_initial.py
contentstore/migrations/0002_messageset_content_type.py
contentstore/migrations/0003_auto_20160513_1115.py
contentstore/migrations/0004_auto_20160810_0916.py
contentstore/migrations/0005_auto_20160912_0923.py
contentstore/migrations/0006_messageset_channel.py
contentstore/migrations/0007_auto_20171102_0950.py
contentstore/migrations/0008_schedule_scheduler_schedule_id.py
contentstore/migrations/0009_add_messageset_label.py
contentstore/migrations/0010_auto_20181126_1104.py
contentstore/migrations/0011_message_metadata.py
contentstore/migrations/__init__.py
contentstore/templates/contentstore/messageset/clone_messageset.html
contentstore/tests/__init__.py
contentstore/tests/test_general.py
contentstore/tests/test_models.py
contentstore/tests/test_signals.py
contentstore/tests/test_tasks.py
contentstore/tests/test_views.py
scheduler/__init__.py
scheduler/client.py
seed_stage_based_messaging/__init__.py
seed_stage_based_messaging/celery.py
seed_stage_based_messaging/decorators.py
seed_stage_based_messaging/settings.py
seed_stage_based_messaging/test_decorators.py
seed_stage_based_messaging/test_utils.py
seed_stage_based_messaging/testsettings.py
seed_stage_based_messaging/urls.py
seed_stage_based_messaging/utils.py
seed_stage_based_messaging/wsgi.py
subscriptions/__init__.py
subscriptions/admin.py
subscriptions/models.py
subscriptions/serializers.py
subscriptions/tasks.py
subscriptions/test_tasks.py
subscriptions/tests.py
subscriptions/urls.py
subscriptions/views.py
seed_stage_based_messaging-0.13.1.dist-info/LICENCE
seed_stage_based_messaging-0.13.1.dist-info/METADATA
seed_stage_based_messaging-0.13.1.dist-info/WHEEL
seed_stage_based_messaging-0.13.1.dist-info/top_level.txt
seed_stage_based_messaging-0.13.1.dist-info/RECORD
